MANIFEST.in
setup.cfg
setup.py
./common/maskApi.c
common/gason.cpp
common/gason.h
common/maskApi.c
common/maskApi.h
pycocotools/__init__.py
pycocotools/_mask.c
pycocotools/_mask.pyx
pycocotools/coco.py
pycocotools/cocoeval.py
pycocotools/mask.py
pycocotools_fix_test.egg-info/PKG-INFO
pycocotools_fix_test.egg-info/SOURCES.txt
pycocotools_fix_test.egg-info/dependency_links.txt
pycocotools_fix_test.egg-info/requires.txt
pycocotools_fix_test.egg-info/top_level.txt